dpanonymize/__init__.py
dpanonymize/__version__.py
dpanonymize/actigraphy/__init__.py
dpanonymize/audio/__init__.py
dpanonymize/mri/__init__.py
dpanonymize/survey/__init__.py
dpanonymize/video/__init__.py
dpanonymize-0.1.data/scripts/dpanon.py
dpanonymize-0.1.dist-info/METADATA
dpanonymize-0.1.dist-info/WHEEL
dpanonymize-0.1.dist-info/top_level.txt
dpanonymize-0.1.dist-info/RECORD
