Metadata-Version: 2.1
Name: dpanonymize
Version: 0.1
Summary: PII remover
Home-page: https://github.com/AMP=SCZ/dpanonymize
Author: DPACC
Author-email: kevincho@bwh.harvard.edu
License: UNKNOWN
Platform: UNKNOWN
Requires-Dist: pandas
